[
 {
  "mfg": "Scanlens",
  "year": 1967,
  "set": "VFL Footballers",
  "variety": "Base",
  "team": "Unknown",
  "player": "John Jillard",
  "no": "1",
  "sku": "1967SCAN1",
  "img": ""
 },
 {
  "mfg": "Scanlens",
  "year": 1967,
  "set": "VFL Footballers",
  "variety": "Base",
  "team": "Unknown",
  "player": "Ian Bryant",
  "no": "2",
  "sku": "1967SCAN2",
  "img": ""
 },
 {
  "mfg": "Scanlens",
  "year": 1967,
  "set": "VFL Footballers",
  "variety": "Base",
  "team": "Unknown",
  "player": "John Schultz",
  "no": "3",
  "sku": "1967SCAN3",
  "img": ""
 },
 {
  "mfg": "Scanlens",
  "year": 1967,
  "set": "VFL Footballers",
  "variety": "Base",
  "team": "Unknown",
  "player": "Greg Brown",
  "no": "4",
  "sku": "1967SCAN4",
  "img": ""
 },
 {
  "mfg": "Scanlens",
  "year": 1967,
  "set": "VFL Footballers",
  "variety": "Base",
  "team": "Unknown",
  "player": "Allan Noonan",
  "no": "5",
  "sku": "1967SCAN5",
  "img": ""
 },
 {
  "mfg": "Scanlens",
  "year": 1967,
  "set": "VFL Footballers",
  "variety": "Base",
  "team": "Unknown",
  "player": "Ken Fraser",
  "no": "6",
  "sku": "1967SCAN6",
  "img": ""
 },
 {
  "mfg": "Scanlens",
  "year": 1967,
  "set": "VFL Footballers",
  "variety": "Base",
  "team": "Unknown",
  "player": "Ted Fordham",
  "no": "7",
  "sku": "1967SCAN7",
  "img": ""
 },
 {
  "mfg": "Scanlens",
  "year": 1967,
  "set": "VFL Footballers",
  "variety": "Base",
  "team": "Unknown",
  "player": "Bob Skilton",
  "no": "8",
  "sku": "1967SCAN8",
  "img": ""
 },
 {
  "mfg": "Scanlens",
  "year": 1967,
  "set": "VFL Footballers",
  "variety": "Base",
  "team": "Unknown",
  "player": "Barry Davis",
  "no": "9",
  "sku": "1967SCAN9",
  "img": ""
 },
 {
  "mfg": "Scanlens",
  "year": 1967,
  "set": "VFL Footballers",
  "variety": "Base",
  "team": "Unknown",
  "player": "Hassa Man",
  "no": "10",
  "sku": "1967SCAN10",
  "img": ""
 },
 {
  "mfg": "Scanlens",
  "year": 1967,
  "set": "VFL Footballers",
  "variety": "Base",
  "team": "Unknown",
  "player": "Neville Crowe",
  "no": "11",
  "sku": "1967SCAN11",
  "img": ""
 },
 {
  "mfg": "Scanlens",
  "year": 1967,
  "set": "VFL Footballers",
  "variety": "Base",
  "team": "Unknown",
  "player": "Ted Whitten",
  "no": "12",
  "sku": "1967SCAN12",
  "img": ""
 },
 {
  "mfg": "Scanlens",
  "year": 1967,
  "set": "VFL Footballers",
  "variety": "Base",
  "team": "Unknown",
  "player": "Geoff Rosenow",
  "no": "13",
  "sku": "1967SCAN13",
  "img": ""
 },
 {
  "mfg": "Scanlens",
  "year": 1967,
  "set": "VFL Footballers",
  "variety": "Base",
  "team": "Unknown",
  "player": "John Sharrock",
  "no": "15",
  "sku": "1967SCAN15",
  "img": ""
 },
 {
  "mfg": "Scanlens",
  "year": 1967,
  "set": "VFL Footballers",
  "variety": "Base",
  "team": "Unknown",
  "player": "Darrell Baldock",
  "no": "16",
  "sku": "1967SCAN16",
  "img": ""
 },
 {
  "mfg": "Scanlens",
  "year": 1967,
  "set": "VFL Footballers",
  "variety": "Base",
  "team": "Unknown",
  "player": "Eric Sarich",
  "no": "17",
  "sku": "1967SCAN17",
  "img": ""
 },
 {
  "mfg": "Scanlens",
  "year": 1967,
  "set": "VFL Footballers",
  "variety": "Base",
  "team": "Unknown",
  "player": "Bob Murray",
  "no": "18",
  "sku": "1967SCAN18",
  "img": ""
 },
 {
  "mfg": "Scanlens",
  "year": 1967,
  "set": "VFL Footballers",
  "variety": "Base",
  "team": "Unknown",
  "player": "Daryl Peoples",
  "no": "19",
  "sku": "1967SCAN19",
  "img": ""
 },
 {
  "mfg": "Scanlens",
  "year": 1967,
  "set": "VFL Footballers",
  "variety": "Base",
  "team": "Unknown",
  "player": "Ian Stewart",
  "no": "20",
  "sku": "1967SCAN20",
  "img": ""
 },
 {
  "mfg": "Scanlens",
  "year": 1967,
  "set": "VFL Footballers",
  "variety": "Base",
  "team": "Unknown",
  "player": "John Newnham",
  "no": "21",
  "sku": "1967SCAN21",
  "img": ""
 },
 {
  "mfg": "Scanlens",
  "year": 1967,
  "set": "VFL Footballers",
  "variety": "Base",
  "team": "Unknown",
  "player": "Pat Guinane",
  "no": "22",
  "sku": "1967SCAN22",
  "img": ""
 },
 {
  "mfg": "Scanlens",
  "year": 1967,
  "set": "VFL Footballers",
  "variety": "Base",
  "team": "Unknown",
  "player": "Des Tuddenham",
  "no": "23",
  "sku": "1967SCAN23",
  "img": ""
 },
 {
  "mfg": "Scanlens",
  "year": 1967,
  "set": "VFL Footballers",
  "variety": "Base",
  "team": "Unknown",
  "player": "Austin Robertson",
  "no": "24",
  "sku": "1967SCAN24",
  "img": ""
 },
 {
  "mfg": "Scanlens",
  "year": 1967,
  "set": "VFL Footballers",
  "variety": "Base",
  "team": "Unknown",
  "player": "Graham Arthur",
  "no": "25",
  "sku": "1967SCAN25",
  "img": ""
 },
 {
  "mfg": "Scanlens",
  "year": 1967,
  "set": "VFL Footballers",
  "variety": "Base",
  "team": "Unknown",
  "player": "Paul Harrison",
  "no": "26",
  "sku": "1967SCAN26",
  "img": ""
 },
 {
  "mfg": "Scanlens",
  "year": 1967,
  "set": "VFL Footballers",
  "variety": "Base",
  "team": "Unknown",
  "player": "Stuart Magee",
  "no": "27",
  "sku": "1967SCAN27",
  "img": ""
 },
 {
  "mfg": "Scanlens",
  "year": 1967,
  "set": "VFL Footballers",
  "variety": "Base",
  "team": "Unknown",
  "player": "Kevin Smith",
  "no": "28",
  "sku": "1967SCAN28",
  "img": ""
 },
 {
  "mfg": "Scanlens",
  "year": 1967,
  "set": "VFL Footballers",
  "variety": "Base",
  "team": "Unknown",
  "player": "Norm Brown",
  "no": "29",
  "sku": "1967SCAN29",
  "img": ""
 },
 {
  "mfg": "Scanlens",
  "year": 1967,
  "set": "VFL Footballers",
  "variety": "Base",
  "team": "Unknown",
  "player": "Bill Barrot",
  "no": "30",
  "sku": "1967SCAN30",
  "img": ""
 },
 {
  "mfg": "Scanlens",
  "year": 1967,
  "set": "VFL Footballers",
  "variety": "Base",
  "team": "Unknown",
  "player": "John Hayes",
  "no": "31",
  "sku": "1967SCAN31",
  "img": ""
 },
 {
  "mfg": "Scanlens",
  "year": 1967,
  "set": "VFL Footballers",
  "variety": "Base",
  "team": "Unknown",
  "player": "Frank Dimattina",
  "no": "32",
  "sku": "1967SCAN32",
  "img": ""
 },
 {
  "mfg": "Scanlens",
  "year": 1967,
  "set": "VFL Footballers",
  "variety": "Base",
  "team": "Unknown",
  "player": "Doug Hellings",
  "no": "33",
  "sku": "1967SCAN33",
  "img": ""
 },
 {
  "mfg": "Scanlens",
  "year": 1967,
  "set": "VFL Footballers",
  "variety": "Base",
  "team": "Unknown",
  "player": "Carl Ditterich",
  "no": "34",
  "sku": "1967SCAN34",
  "img": ""
 },
 {
  "mfg": "Scanlens",
  "year": 1967,
  "set": "VFL Footballers",
  "variety": "Base",
  "team": "Unknown",
  "player": "Don McKenzie",
  "no": "35",
  "sku": "1967SCAN35",
  "img": ""
 },
 {
  "mfg": "Scanlens",
  "year": 1967,
  "set": "VFL Footballers",
  "variety": "Base",
  "team": "Unknown",
  "player": "Darryl Griffiths",
  "no": "36",
  "sku": "1967SCAN36",
  "img": ""
 },
 {
  "mfg": "Scanlens",
  "year": 1967,
  "set": "VFL Footballers",
  "variety": "Base",
  "team": "Unknown",
  "player": "Melbourne Players",
  "no": "2",
  "sku": "1967SCAN2",
  "img": ""
 },
 {
  "mfg": "Scanlens",
  "year": 1967,
  "set": "VFL Footballers",
  "variety": "Base",
  "team": "Unknown",
  "player": "Nth Melb Players",
  "no": "2",
  "sku": "1967SCAN2",
  "img": ""
 },
 {
  "mfg": "Scanlens",
  "year": 1967,
  "set": "VFL Footballers",
  "variety": "Base",
  "team": "Unknown",
  "player": "Essendon Players",
  "no": "3",
  "sku": "1967SCAN3",
  "img": ""
 },
 {
  "mfg": "Scanlens",
  "year": 1967,
  "set": "VFL Footballers",
  "variety": "Base",
  "team": "Unknown",
  "player": "Max Pitt",
  "no": "40",
  "sku": "1967SCAN40",
  "img": ""
 },
 {
  "mfg": "Scanlens",
  "year": 1967,
  "set": "VFL Footballers",
  "variety": "Base",
  "team": "Unknown",
  "player": "Ian Montgomery",
  "no": "41",
  "sku": "1967SCAN41",
  "img": ""
 },
 {
  "mfg": "Scanlens",
  "year": 1967,
  "set": "VFL Footballers",
  "variety": "Base",
  "team": "Unknown",
  "player": "Wayne Richardson",
  "no": "42",
  "sku": "1967SCAN42",
  "img": ""
 },
 {
  "mfg": "Scanlens",
  "year": 1967,
  "set": "VFL Footballers",
  "variety": "Base",
  "team": "Unknown",
  "player": "Len Thompson",
  "no": "43",
  "sku": "1967SCAN43",
  "img": ""
 },
 {
  "mfg": "Scanlens",
  "year": 1967,
  "set": "VFL Footballers",
  "variety": "Base",
  "team": "Unknown",
  "player": "John Gill",
  "no": "44",
  "sku": "1967SCAN44",
  "img": ""
 },
 {
  "mfg": "Scanlens",
  "year": 1967,
  "set": "VFL Footballers",
  "variety": "Base",
  "team": "Unknown",
  "player": "Ian Collins",
  "no": "45",
  "sku": "1967SCAN45",
  "img": ""
 },
 {
  "mfg": "Scanlens",
  "year": 1967,
  "set": "VFL Footballers",
  "variety": "Base",
  "team": "Unknown",
  "player": "Collingwood Players",
  "no": "4",
  "sku": "1967SCAN4",
  "img": ""
 },
 {
  "mfg": "Scanlens",
  "year": 1967,
  "set": "VFL Footballers",
  "variety": "Base",
  "team": "Unknown",
  "player": "StKilda Players",
  "no": "3",
  "sku": "1967SCAN3",
  "img": ""
 },
 {
  "mfg": "Scanlens",
  "year": 1967,
  "set": "VFL Footballers",
  "variety": "Base",
  "team": "Unknown",
  "player": "Fitzroy Players",
  "no": "2",
  "sku": "1967SCAN2",
  "img": ""
 },
 {
  "mfg": "Scanlens",
  "year": 1967,
  "set": "VFL Footballers",
  "variety": "Base",
  "team": "Unknown",
  "player": "Richmond Players",
  "no": "2",
  "sku": "1967SCAN2",
  "img": ""
 },
 {
  "mfg": "Scanlens",
  "year": 1967,
  "set": "VFL Footballers",
  "variety": "Base",
  "team": "Unknown",
  "player": "Hawthorn Players",
  "no": "4",
  "sku": "1967SCAN4",
  "img": ""
 },
 {
  "mfg": "Scanlens",
  "year": 1967,
  "set": "VFL Footballers",
  "variety": "Base",
  "team": "Unknown",
  "player": "Geelong Players",
  "no": "4",
  "sku": "1967SCAN4",
  "img": ""
 },
 {
  "mfg": "Scanlens",
  "year": 1967,
  "set": "VFL Footballers",
  "variety": "Base",
  "team": "Unknown",
  "player": "Wes Lofts",
  "no": "52",
  "sku": "1967SCAN52",
  "img": ""
 },
 {
  "mfg": "Scanlens",
  "year": 1967,
  "set": "VFL Footballers",
  "variety": "Base",
  "team": "Unknown",
  "player": "Ron Barassi",
  "no": "53",
  "sku": "1967SCAN53",
  "img": ""
 },
 {
  "mfg": "Scanlens",
  "year": 1967,
  "set": "VFL Footballers",
  "variety": "Base",
  "team": "Unknown",
  "player": "Adrian Gallagher",
  "no": "54",
  "sku": "1967SCAN54",
  "img": ""
 },
 {
  "mfg": "Scanlens",
  "year": 1967,
  "set": "VFL Footballers",
  "variety": "Base",
  "team": "Unknown",
  "player": "John Ibrahams",
  "no": "55",
  "sku": "1967SCAN55",
  "img": ""
 },
 {
  "mfg": "Scanlens",
  "year": 1967,
  "set": "VFL Footballers",
  "variety": "Base",
  "team": "Unknown",
  "player": "Ian Robertson",
  "no": "56",
  "sku": "1967SCAN56",
  "img": ""
 },
 {
  "mfg": "Scanlens",
  "year": 1967,
  "set": "VFL Footballers",
  "variety": "Base",
  "team": "Unknown",
  "player": "Noel Teasdale",
  "no": "57",
  "sku": "1967SCAN57",
  "img": ""
 },
 {
  "mfg": "Scanlens",
  "year": 1967,
  "set": "VFL Footballers",
  "variety": "Base",
  "team": "Unknown",
  "player": "Footscray Players",
  "no": "3",
  "sku": "1967SCAN3",
  "img": ""
 },
 {
  "mfg": "Scanlens",
  "year": 1967,
  "set": "VFL Footballers",
  "variety": "Base",
  "team": "Unknown",
  "player": "South Melb Players",
  "no": "3",
  "sku": "1967SCAN3",
  "img": ""
 },
 {
  "mfg": "Scanlens",
  "year": 1967,
  "set": "VFL Footballers",
  "variety": "Base",
  "team": "Unknown",
  "player": "Bernie Massey",
  "no": "60",
  "sku": "1967SCAN60",
  "img": ""
 },
 {
  "mfg": "Scanlens",
  "year": 1967,
  "set": "VFL Footballers",
  "variety": "Base",
  "team": "Unknown",
  "player": "Barry Bourke",
  "no": "61",
  "sku": "1967SCAN61",
  "img": ""
 },
 {
  "mfg": "Scanlens",
  "year": 1967,
  "set": "VFL Footballers",
  "variety": "Base",
  "team": "Unknown",
  "player": "Roy West",
  "no": "62",
  "sku": "1967SCAN62",
  "img": ""
 },
 {
  "mfg": "Scanlens",
  "year": 1967,
  "set": "VFL Footballers",
  "variety": "Base",
  "team": "Unknown",
  "player": "John Dugdale",
  "no": "64",
  "sku": "1967SCAN64",
  "img": ""
 },
 {
  "mfg": "Scanlens",
  "year": 1967,
  "set": "VFL Footballers",
  "variety": "Base",
  "team": "Unknown",
  "player": "Max Dowdle",
  "no": "65",
  "sku": "1967SCAN65",
  "img": ""
 },
 {
  "mfg": "Scanlens",
  "year": 1967,
  "set": "VFL Footballers",
  "variety": "Base",
  "team": "Unknown",
  "player": "Frank Goode",
  "no": "66",
  "sku": "1967SCAN66",
  "img": ""
 },
 {
  "mfg": "Scanlens",
  "year": 1967,
  "set": "VFL Footballers",
  "variety": "Base",
  "team": "Unknown",
  "player": "Phil Lade",
  "no": "67",
  "sku": "1967SCAN67",
  "img": ""
 },
 {
  "mfg": "Scanlens",
  "year": 1967,
  "set": "VFL Footballers",
  "variety": "Base",
  "team": "Unknown",
  "player": "Peter Crimmins",
  "no": "68",
  "sku": "1967SCAN68",
  "img": ""
 },
 {
  "mfg": "Scanlens",
  "year": 1967,
  "set": "VFL Footballers",
  "variety": "Base",
  "team": "Unknown",
  "player": "Ray Wilson",
  "no": "69",
  "sku": "1967SCAN69",
  "img": ""
 },
 {
  "mfg": "Scanlens",
  "year": 1967,
  "set": "VFL Footballers",
  "variety": "Base",
  "team": "Unknown",
  "player": "Ken Beck",
  "no": "70",
  "sku": "1967SCAN70",
  "img": ""
 },
 {
  "mfg": "Scanlens",
  "year": 1967,
  "set": "VFL Footballers",
  "variety": "Base",
  "team": "Unknown",
  "player": "Ray Groom",
  "no": "71",
  "sku": "1967SCAN71",
  "img": ""
 },
 {
  "mfg": "Scanlens",
  "year": 1967,
  "set": "VFL Footballers",
  "variety": "Base",
  "team": "Unknown",
  "player": "Bruce Kenneally",
  "no": "72",
  "sku": "1967SCAN72",
  "img": ""
 }
]